{
    "crystal structure":"\u200btetragonal[2]",
    "per shell":"2, 8, 18, 32, 20, 9, 2",
    "Z":"91",
    "density":" near r.t.15.37 g/cm3",
    "oxidation states":"2, 3, 4, 5 \u200b(a weakly basic oxide)",
    "heat of vaporizatio":"481 kJ/mol",
    "magnetic ordering":"paramagnetic[4]",
    "atomic weight":" (\u00b1) (Ar)231.03588(2)[1]",
    "boiling point":"4300 K \u200b(4027 \u00b0C, \u200b7280 \u00b0F) (?)",
    "heat of fusion":"12.34 kJ/mol",
    "appearance":"bright, silvery metallic luster",
    "thermal conductivity":"47 W/(m\u00b7K)",
    "covalent radius":"200 pm",
    "phase":"solid",
    "category":"  actinide",
    "electronegativity":" 1.5",
    "symbol":"protactinium, Pa",
    "Group, block":"group n/a, f-block",
    "period":"period 7",
    "melting point":"1841 K \u200b(1568 \u00b0C, \u200b2854 \u00b0F)",
    "configuration":"[Rn] 5f2 6d1 7s2",
    "cas number":"7440-13-3"
}